django_plugin_django_debug_toolbar/__init__.py
django_plugin_django_debug_toolbar-0.5.2.dist-info/WHEEL
django_plugin_django_debug_toolbar-0.5.2.dist-info/entry_points.txt
django_plugin_django_debug_toolbar-0.5.2.dist-info/METADATA
django_plugin_django_debug_toolbar-0.5.2.dist-info/RECORD
