Metadata-Version: 2.3
Name: django-plugin-django-debug-toolbar
Version: 0.5.2
Summary: Django plugin that configures the Django Debug Toolbar
Author: Tom Viner
License: Apache-2.0
Classifier: License :: OSI Approved :: Apache Software License
Requires-Dist: django
Requires-Dist: djp
Requires-Dist: django-debug-toolbar<6.0.0
Requires-Dist: pytest ; extra == 'test'
Requires-Dist: pytest-django ; extra == 'test'
Requires-Dist: pytest-cov ; extra == 'test'
Requires-Dist: rust-just ; extra == 'test'
Requires-Dist: ruff ; extra == 'test'
Requires-Dist: typos ; extra == 'test'
Project-URL: CI, https://github.com/tomviner/django-plugin-django-debug-toolbar/actions
Project-URL: Changelog, https://github.com/tomviner/django-plugin-django-debug-toolbar/releases
Project-URL: Homepage, https://github.com/tomviner/django-plugin-django-debug-toolbar
Project-URL: Issues, https://github.com/tomviner/django-plugin-django-debug-toolbar/issues
Provides-Extra: test
